{
  "bao": {
    "password_hash": "123",
    "email": "",
    "created_at": "2025-03-21T16:19:29.607232",
    "status": "online",
    "channels_owned": [
      "baosd",
      "newbao"
    ],
    "channels_joined": [
      "baosd",
      "newbao",
      "aob cool chat"
    ]
  },
  "aob": {
    "password_hash": "321",
    "email": "",
    "created_at": "2025-03-21T16:29:20.292132",
    "status": "online",
    "channels_owned": [
      "aob cool chat"
    ],
    "channels_joined": [
      "baosd",
      "newbao",
      "aob cool chat"
    ]
  },
  "hacker": {
    "password_hash": "456",
    "email": "",
    "created_at": "2025-03-26T22:15:47.472700",
    "status": "invisible",
    "channels_owned": [],
    "channels_joined": [
      "baosd",
      "newbao",
      "aob cool chat"
    ]
  }
}